ldap_mcp/__init__.py
ldap_mcp/config.py
ldap_mcp/connection.py
ldap_mcp/errors.py
ldap_mcp/models.py
ldap_mcp/prompts/__init__.py
ldap_mcp/prompts/group_members.py
ldap_mcp/prompts/group_membership.py
ldap_mcp/prompts/search_guide.py
ldap_mcp/prompts/user_lookup.py
ldap_mcp/server.py
ldap_mcp/tools/__init__.py
ldap_mcp/tools/_context.py
ldap_mcp/tools/_helpers.py
ldap_mcp/tools/compare.py
ldap_mcp/tools/entry.py
ldap_mcp/tools/schema.py
ldap_mcp/tools/search.py
ldap_mcp-0.1.1.dist-info/WHEEL
ldap_mcp-0.1.1.dist-info/entry_points.txt
ldap_mcp-0.1.1.dist-info/METADATA
ldap_mcp-0.1.1.dist-info/RECORD
