Metadata-Version: 2.4
Name: ldap-mcp
Version: 0.1.1
Summary: MCP server for LDAP directory operations
Keywords: mcp,ldap,directory,model-context-protocol
Author: Major Hayden
Author-email: Major Hayden <major@mhtx.net>
License-Expression: MIT
Classifier: Development Status :: 3 - Alpha
Classifier: Intended Audience :: Developers
Classifier: License :: OSI Approved :: MIT License
Classifier: Programming Language :: Python :: 3.13
Classifier: Programming Language :: Python :: 3.14
Classifier: Topic :: System :: Systems Administration :: Authentication/Directory :: LDAP
Classifier: Typing :: Typed
Requires-Dist: fastmcp>=3.0.0b1
Requires-Dist: ldap3>=2.9
Requires-Dist: pydantic-settings>=2.0.0
Requires-Python: >=3.13
Project-URL: Homepage, https://github.com/major/ldap-mcp
Project-URL: Repository, https://github.com/major/ldap-mcp
